ai_data_validator/__init__.py
ai_data_validator/report.py
ai_data_validator-0.2.0.dist-info/METADATA
ai_data_validator-0.2.0.dist-info/WHEEL
ai_data_validator-0.2.0.dist-info/top_level.txt
ai_data_validator-0.2.0.dist-info/RECORD
