Metadata-Version: 2.4
Name: ai-data-validator
Version: 0.2.0
Summary: A production-ready data validation and PII redaction library for AI services, featuring validation reports and custom redaction strategies.
Author-email: Venkata Sai Bharadwaj Velamakanni <venkata242000@gmail.com>
License: MIT License
Project-URL: Homepage, https://github.com/venvelamakanni/ai-data-validator
Project-URL: Issues, https://github.com/venvelamakanni/ai-data-validator/issues
Classifier: Programming Language :: Python :: 3
Classifier: License :: OSI Approved :: MIT License
Classifier: Operating System :: OS Independent
Classifier: Intended Audience :: Developers
Classifier: Topic :: Security
Classifier: Topic :: Software Development :: Libraries
Requires-Python: >=3.8
Requires-Dist: pydantic>=2.0
Requires-Dist: presidio-analyzer>=2.2
Requires-Dist: presidio-anonymizer>=2.2
Requires-Dist: spacy>=3.0
